reqreq/__init__.py
reqreq/test.py
reqreq-0.0.0.dist-info/METADATA
reqreq-0.0.0.dist-info/WHEEL
reqreq-0.0.0.dist-info/top_level.txt
reqreq-0.0.0.dist-info/RECORD
