Metadata-Version: 2.1
Name: reqreq
Version: 0.0.0
Summary: A tool that can make GET and POST requests in parallel
Home-page: https://github.co.jp/
Author: bib_inf
Author-email: contact.bibinf@gmail.com
License: CC0 v1.0
Classifier: Programming Language :: Python :: 3
Classifier: Topic :: Software Development :: Libraries
Classifier: License :: CC0 1.0 Universal (CC0 1.0) Public Domain Dedication
Requires-Dist: ezpip
Requires-Dist: relpath (>=3.0.5)
Requires-Dist: mulmap
Requires-Dist: requests
